LICENSE
README.md
setup.py
src/paratc/__init__.py
src/paratc/_const.py
src/paratc/_make_example_data.py
src/paratc/_output_formats.py
src/paratc/_utils.py
src/paratc/_version.py
src/paratc/bg_models.py
src/paratc/bl_models.py
src/paratc/inflow_models.py
src/paratc/rmw_models.py
src/paratc/stress_models.py
src/paratc/tctools.py
src/paratc/track_tools.py
src/paratc.egg-info/PKG-INFO
src/paratc.egg-info/SOURCES.txt
src/paratc.egg-info/dependency_links.txt
src/paratc.egg-info/requires.txt
src/paratc.egg-info/top_level.txt
src/paratc/tc_models/__init__.py
src/paratc/tc_models/_holland1980.py
src/paratc/tc_models/_tc_model.py