Metadata-Version: 2.1
Name: paratc
Version: 0.2.2
Summary: Functions for creating parametric tropical cyclone models.
Home-page: https://github.com/davbyr/ParaTC
Author: David Byrne
Author-email: dbyrne@woodwellclimate.org
License-File: LICENSE
